charm/__init__.py
charm/config.py
charm/adapters/__init__.py
charm/adapters/abenc_adapt_hybrid.py
charm/adapters/dabenc_adapt_hybrid.py
charm/adapters/ibenc_adapt_hybrid.py
charm/adapters/ibenc_adapt_identityhash.py
charm/adapters/kpabenc_adapt_hybrid.py
charm/adapters/pkenc_adapt_bchk05.py
charm/adapters/pkenc_adapt_chk04.py
charm/adapters/pkenc_adapt_hybrid.py
charm/adapters/pksig_adapt_naor01.py
charm/core/__init__.py
charm/core/benchmark.so
charm/core/crypto/__init__.py
charm/core/crypto/AES.so
charm/core/crypto/cryptobase.so
charm/core/crypto/DES.so
charm/core/crypto/DES3.so
charm/core/engine/__init__.py
charm/core/engine/protocol.py
charm/core/engine/util.py
charm/core/math/__init__.py
charm/core/math/elliptic_curve.so
charm/core/math/integer.so
charm/core/math/pairing.so
charm/schemes/__init__.py
charm/schemes/chamhash_adm05.py
charm/schemes/chamhash_rsa_hw09.py
charm/schemes/dabe_aw11.py
charm/schemes/encap_bchk05.py
charm/schemes/joye_scheme.py
charm/schemes/lem_scheme.py
charm/schemes/pk_fre_ccv11.py
charm/schemes/pk_vrf.py
charm/schemes/pre_mg07.py
charm/schemes/protocol_a01.py
charm/schemes/protocol_ao00.py
charm/schemes/protocol_cns07.py
charm/schemes/protocol_schnorr91.py
charm/schemes/sigma1.py
charm/schemes/sigma2.py
charm/schemes/sigma3.py
charm/schemes/abenc/__init__.py
charm/schemes/abenc/abenc_bsw07.py
charm/schemes/abenc/abenc_lsw08.py
charm/schemes/abenc/abenc_waters09.py
charm/schemes/abenc/abenc_yct14.py
charm/schemes/abenc/dac-macs-yang-14.py
charm/schemes/abenc/dfa_fe12.py
charm/schemes/abenc/maabe-yang-14.py
charm/schemes/abenc/pk_hve08.py
charm/schemes/abenc/tbpre-liu-14.py
charm/schemes/commit/__init__.py
charm/schemes/commit/commit_gs08.py
charm/schemes/commit/commit_pedersen92.py
charm/schemes/grpsig/__init__.py
charm/schemes/grpsig/groupsig_bgls04.py
charm/schemes/grpsig/groupsig_bgls04_var.py
charm/schemes/hibenc/__init__.py
charm/schemes/hibenc/hibenc_bb04.py
Charm_Crypto-0.43.dist-info/DESCRIPTION.rst
Charm_Crypto-0.43.dist-info/METADATA
Charm_Crypto-0.43.dist-info/metadata.json
Charm_Crypto-0.43.dist-info/RECORD
Charm_Crypto-0.43.dist-info/top_level.txt
Charm_Crypto-0.43.dist-info/WHEEL
