Metadata-Version: 2.0
Name: Charm-Crypto
Version: 0.43
Summary: Charm is a framework for rapid prototyping of cryptosystems
Home-page: http://charm-crypto.com/
Author: J. Ayo Akinyele
Author-email: ayo.akinyele@charm-crypto.com
License: LGPL
Platform: UNKNOWN
Requires-Dist: setuptools
Requires-Dist: pyparsing (>=1.5.5)
